AUTHORS.md
LICENSE
MANIFEST.in
README.md
pyproject.toml
setup.cfg
setup.py
django_oci/__init__.py
django_oci/admin.py
django_oci/apps.py
django_oci/auth.py
django_oci/files.py
django_oci/models.py
django_oci/settings.py
django_oci/signals.py
django_oci/storage.py
django_oci/urls.py
django_oci/utils.py
django_oci.egg-info/PKG-INFO
django_oci.egg-info/SOURCES.txt
django_oci.egg-info/dependency_links.txt
django_oci.egg-info/not-zip-safe
django_oci.egg-info/requires.txt
django_oci.egg-info/top_level.txt
django_oci/views/__init__.py
django_oci/views/auth.py
django_oci/views/base.py
django_oci/views/blobs.py
django_oci/views/image.py
django_oci/views/parsers.py