Metadata-Version: 2.1
Name: django-oci
Version: 0.0.17
Summary: Open Containers distribution API for Django
Home-page: https://github.com/vsoch/django-oci
Author: Vanessa Sochat
Author-email: vsochat@stanford.edu
License: Apache Software License 2.0
Keywords: django-oci
Platform: UNKNOWN
Classifier: Development Status :: 3 - Alpha
Classifier: Framework :: Django :: 1.11
Classifier: Framework :: Django :: 2.1
Classifier: Intended Audience :: Developers
Classifier: License :: OSI Approved :: BSD License
Classifier: Natural Language :: English
Classifier: Programming Language :: Python :: 3.7
License-File: LICENSE
License-File: AUTHORS.md
